Regression.py
RegressionLibrary-0.3.dist-info/LICENSE
RegressionLibrary-0.3.dist-info/LICENSE.save
RegressionLibrary-0.3.dist-info/METADATA
RegressionLibrary-0.3.dist-info/WHEEL
RegressionLibrary-0.3.dist-info/top_level.txt
RegressionLibrary-0.3.dist-info/RECORD
