Metadata-Version: 2.1
Name: RegressionLibrary
Version: 0.3
Summary: Educational regression models built from scratch in Python
Home-page: https://github.com/Alouakhalid/RegressionLibrary
Author: Ali Khalid Ali Khalid
Author-email: ali88883737@gmail.com
License: UNKNOWN
Platform: UNKNOWN
Classifier: Programming Language :: Python :: 3
Classifier: License :: OSI Approved :: MIT License
Classifier: Operating System :: OS Independent
Requires-Python: >=3.6
License-File: LICENSE
License-File: LICENSE.save
Requires-Dist: numpy
Requires-Dist: tqdm
